bdd_coder/__init__.py
bdd_coder/coders.py
bdd_coder/commands.py
bdd_coder/decorators.py
bdd_coder/exceptions.py
bdd_coder/features.py
bdd_coder/stock.py
bdd_coder/tester.py
bdd_coder/text_utils.py
example/__init__.py
example/advanced_tests/__init__.py
example/advanced_tests/base.py
example/advanced_tests/test_stories.py
example/new_advanced_tests/__init__.py
example/new_advanced_tests/base.py
example/new_advanced_tests/test_stories.py
example/new_tests/__init__.py
example/new_tests/base.py
example/new_tests/test_stories.py
example/tests/__init__.py
example/tests/base.py
example/tests/test_stories.py
example/wrong_tests/__init__.py
example/wrong_tests/base.py
example/wrong_tests/test_stories_duplicate_scenario.py
example/wrong_tests/test_stories_not_inherited.py
example/wrong_tests/test_stories_odd_scenario.py
example/wrong_tests/test_stories_redeclared_param.py
example/wrong_tests/test_stories_repeated_param.py
example/wrong_tests/test_stories_wrong_param_values.py
bdd_coder-2.2.1.dist-info/LICENSE
bdd_coder-2.2.1.dist-info/METADATA
bdd_coder-2.2.1.dist-info/WHEEL
bdd_coder-2.2.1.dist-info/entry_points.txt
bdd_coder-2.2.1.dist-info/top_level.txt
bdd_coder-2.2.1.dist-info/RECORD
