Metadata-Version: 2.1
Name: bdd-coder
Version: 2.2.1
Summary: Gherkin language in class-based tests - test suite blueprinting
Home-page: https://bitbucket.org/coleopter/bdd-coder
Author: Daniel Farré Manzorro
Author-email: d.farre.m@gmail.com
License: UNKNOWN
Platform: UNKNOWN
Classifier: Programming Language :: Python :: 3
Classifier: Programming Language :: Python :: 3.6
Classifier: Programming Language :: Python :: 3.7
Classifier: Programming Language :: Python :: 3.8
Classifier: Programming Language :: Python :: 3.9
Classifier: License :: OSI Approved :: MIT License
Classifier: Operating System :: OS Independent
Classifier: Environment :: Console
Classifier: Intended Audience :: Developers
Requires-Dist: flake8
Requires-Dist: pygments
Requires-Dist: pytest
Requires-Dist: pyyaml
Requires-Dist: simple-cmd
Provides-Extra: dev
Requires-Dist: ipdb ; extra == 'dev'
Requires-Dist: ipython ; extra == 'dev'
Provides-Extra: test
Requires-Dist: Twisted ; extra == 'test'
Requires-Dist: freezegun ; extra == 'test'
Requires-Dist: pytest-cov ; extra == 'test'
Requires-Dist: pytest-twisted ; extra == 'test'
